embedding_utils/__init__.py
embedding_utils/embedding_cache.py
embedding_utils/embedding_model.py
embedding_utils-0.1.4.dist-info/METADATA
embedding_utils-0.1.4.dist-info/WHEEL
embedding_utils-0.1.4.dist-info/top_level.txt
embedding_utils-0.1.4.dist-info/RECORD
