Metadata-Version: 2.2
Name: embedding-utils
Version: 0.1.4
Summary: A library for text embeddings with caching.
Author-email: Daniel Ariza <danielarizae@gmail.com>
License: MIT
Classifier: Programming Language :: Python :: 3
Classifier: Programming Language :: Python :: 3.10
Classifier: License :: OSI Approved :: MIT License
Classifier: Operating System :: OS Independent
Requires-Python: <3.12,>=3.10
Requires-Dist: torch<3.0,>=2.0
Requires-Dist: sentence-transformers<4.0,>=2.2
Requires-Dist: device-selector>=0.1.0
Provides-Extra: test
Requires-Dist: pytest>=7.0; extra == "test"
